{
    "compilers": [
        {
            "target": "x86_64-apple-darwin",
            "link": "https://github.com/Andersbakken/rtags-releases/raw/gh-pages/rtags.tar.bz2",
            "major": 3,
            "minor": 2,
            "type": "clang"
        },
        {
            "target": "i386-apple-darwin",
            "link": "https://github.com/Andersbakken/rtags-releases/raw/gh-pages/rtags.tar.bz2",
            "major": 3,
            "minor": 2,
            "type": "clang"
        }
    ]
}
